LICENSE
README
setup.py
paintera/__init__.py
paintera/javafx_modules.py
paintera/version.py
paintera.egg-info/PKG-INFO
paintera.egg-info/SOURCES.txt
paintera.egg-info/dependency_links.txt
paintera.egg-info/entry_points.txt
paintera.egg-info/requires.txt
paintera.egg-info/top_level.txt