Metadata-Version: 2.1
Name: paintera
Version: 0.34.1
Summary: paintera
Home-page: https://github.com/saalfeldlab/paintera
Author: Philipp Hanslovsky
Author-email: hanslovskyp@janelia.hhmi.org
Maintainer: Caleb Hulbert
Maintainer-email: hulbertc@janelia.hmmi.org
License: UNKNOWN
Platform: UNKNOWN
License-File: LICENSE
